{
  "chainId": "penumbra-testnet-deimos-8",
  "ibcConnections": [
    {
      "addressPrefix": "osmo",
      "chainId": "osmo-test-5",
      "channelId": "channel-5",
      "counterpartyChannelId": "channel-8007",
      "displayName": "Osmosis",
      "images": [
        {
          "svg": "https://raw.githubusercontent.com/cosmos/chain-registry/f1348793beb994c6cc0256ed7ebdb48c7aa70003/osmosis/images/osmo.svg"
        }
      ]
    },
    {
      "addressPrefix": "noble",
      "chainId": "grand-1",
      "channelId": "channel-6",
      "counterpartyChannelId": "channel-176",
      "displayName": "Noble",
      "images": [
        {
          "svg": "https://raw.githubusercontent.com/cosmos/chain-registry/2ca39d0e4eaf3431cca13991948e099801f02e46/noble/images/stake.svg"
        }
      ]
    }
  ],
  "rpcs": [
    {
      "name": "Penumbra Labs Testnet RPC",
      "url": "https://grpc.testnet.penumbra.zone",
      "images": [
        {
          "png": "https://raw.githubusercontent.com/prax-wallet/registry/main/images/penumbra-favicon.png"
        }
      ]
    }
  ],
  "assetById": {
    "/5AHh95RAybBbUhQ5zXMWCvstH4rRK/5KMVIVGQltAw=": {
      "denomUnits": [
        {
          "denom": "udelegation_penumbravalid1gjdvn0u85rgldqk5adfexn6n4y8d2m3tfla54sc4gu95xwpzssxsjutk7u"
        },
        {
          "denom": "mdelegation_penumbravalid1gjdvn0u85rgldqk5adfexn6n4y8d2m3tfla54sc4gu95xwpzssxsjutk7u",
          "exponent": 3
        },
        {
          "denom": "delegation_penumbravalid1gjdvn0u85rgldqk5adfexn6n4y8d2m3tfla54sc4gu95xwpzssxsjutk7u",
          "exponent": 6
        }
      ],
      "base": "udelegation_penumbravalid1gjdvn0u85rgldqk5adfexn6n4y8d2m3tfla54sc4gu95xwpzssxsjutk7u",
      "display": "delegation_penumbravalid1gjdvn0u85rgldqk5adfexn6n4y8d2m3tfla54sc4gu95xwpzssxsjutk7u",
      "symbol": "delUM(Starling Staking)",
      "penumbraAssetId": {
        "inner": "/5AHh95RAybBbUhQ5zXMWCvstH4rRK/5KMVIVGQltAw="
      },
      "images": [
        {
          "svg": "https://raw.githubusercontent.com/prax-wallet/registry/main/images/starling-staking.svg"
        }
      ]
    },
    "4r8PcN/HkX0W/eeEKFUQijIESu8YEC8Fec+h8qO1rgU=": {
      "description": "The native token of Osmosis",
      "denomUnits": [
        {
          "denom": "transfer/channel-5/uosmo"
        },
        {
          "denom": "transfer/channel-5/osmo",
          "exponent": 6
        }
      ],
      "base": "transfer/channel-5/uosmo",
      "display": "transfer/channel-5/osmo",
      "name": "Osmosis Testnet",
      "symbol": "OSMO",
      "penumbraAssetId": {
        "inner": "4r8PcN/HkX0W/eeEKFUQijIESu8YEC8Fec+h8qO1rgU="
      },
      "images": [
        {
          "png": "https://raw.githubusercontent.com/cosmos/chain-registry/master/osmosis/images/osmo.png",
          "svg": "https://raw.githubusercontent.com/cosmos/chain-registry/master/osmosis/images/osmo.svg"
        }
      ]
    },
    "6KBVsPINa8gWSHhfH+kAFJC4afEJA3EtuB2HyCqJUws=": {
      "denomUnits": [
        {
          "denom": "cube"
        }
      ],
      "base": "cube",
      "display": "cube",
      "symbol": "CUBE",
      "penumbraAssetId": {
        "inner": "6KBVsPINa8gWSHhfH+kAFJC4afEJA3EtuB2HyCqJUws="
      }
    },
    "DOqaAC7a90KP3405fvLRG4rumqMB4tzKa7XsU3CcdxE=": {
      "description": "USD Coin",
      "denomUnits": [
        {
          "denom": "transfer/channel-6/uusdc"
        },
        {
          "denom": "transfer/channel-6/usdc",
          "exponent": 6
        }
      ],
      "base": "transfer/channel-6/uusdc",
      "display": "transfer/channel-6/usdc",
      "name": "USD Coin",
      "symbol": "USDC",
      "penumbraAssetId": {
        "inner": "DOqaAC7a90KP3405fvLRG4rumqMB4tzKa7XsU3CcdxE="
      },
      "images": [
        {
          "svg": "https://raw.githubusercontent.com/cosmos/chain-registry/master/_non-cosmos/ethereum/images/usdc.svg"
        }
      ]
    },
    "H0dAkstiWmRZIIu8BM8IQioPVl7i+isElLWajNOntQ8=": {
      "description": "The controlled staking asset for Noble Chain",
      "denomUnits": [
        {
          "denom": "transfer/channel-6/ustake"
        },
        {
          "denom": "transfer/channel-6/stake",
          "exponent": 6
        }
      ],
      "base": "transfer/channel-6/ustake",
      "display": "transfer/channel-6/stake",
      "name": "Stake",
      "symbol": "STAKE",
      "penumbraAssetId": {
        "inner": "H0dAkstiWmRZIIu8BM8IQioPVl7i+isElLWajNOntQ8="
      }
    },
    "HLkKbVfA72oQaMdYFroWQ1qoSyl/KLHZiOMJhL2y9w0=": {
      "denomUnits": [
        {
          "denom": "test_eth",
          "exponent": 18
        },
        {
          "denom": "wtest_eth"
        }
      ],
      "base": "wtest_eth",
      "display": "test_eth",
      "symbol": "TestETH",
      "penumbraAssetId": {
        "inner": "HLkKbVfA72oQaMdYFroWQ1qoSyl/KLHZiOMJhL2y9w0="
      }
    },
    "HW2Eq3UZVSBttoUwUi/MUtE7rr2UU7/UH500byp7OAc=": {
      "denomUnits": [
        {
          "denom": "gm",
          "exponent": 6
        },
        {
          "denom": "mgm",
          "exponent": 3
        },
        {
          "denom": "ugm"
        }
      ],
      "base": "ugm",
      "display": "gm",
      "symbol": "GM",
      "penumbraAssetId": {
        "inner": "HW2Eq3UZVSBttoUwUi/MUtE7rr2UU7/UH500byp7OAc="
      },
      "images": [
        {
          "svg": "https://raw.githubusercontent.com/prax-wallet/registry/main/images/full-moon-face.svg"
        }
      ]
    },
    "KeqcLzNx9qSH5+lcJHBB9KNW+YPrBk5dKzvPMiypahA=": {
      "denomUnits": [
        {
          "denom": "penumbra",
          "exponent": 6
        },
        {
          "denom": "mpenumbra",
          "exponent": 3
        },
        {
          "denom": "upenumbra"
        }
      ],
      "base": "upenumbra",
      "display": "penumbra",
      "symbol": "UM",
      "penumbraAssetId": {
        "inner": "KeqcLzNx9qSH5+lcJHBB9KNW+YPrBk5dKzvPMiypahA="
      },
      "images": [
        {
          "svg": "https://raw.githubusercontent.com/prax-wallet/registry/main/images/um.svg"
        }
      ]
    },
    "M9YkqCHcD0SLIb0phwFWRAWXF10ovNe8DcQTiszO4QY=": {
      "denomUnits": [
        {
          "denom": "transfer/channel-5/uion"
        },
        {
          "denom": "transfer/channel-5/ion",
          "exponent": 6
        }
      ],
      "base": "transfer/channel-5/uion",
      "display": "transfer/channel-5/ion",
      "name": "Ion",
      "symbol": "ION",
      "penumbraAssetId": {
        "inner": "M9YkqCHcD0SLIb0phwFWRAWXF10ovNe8DcQTiszO4QY="
      },
      "images": [
        {
          "png": "https://raw.githubusercontent.com/cosmos/chain-registry/master/osmosis/images/ion.png",
          "svg": "https://raw.githubusercontent.com/cosmos/chain-registry/master/osmosis/images/ion.svg"
        }
      ]
    },
    "Pc1lr9eCdoKTkBJCCia9egZdG/qGdMg4WFDhWmXr7Q8=": {
      "description": "Love is a test tokenfactory asset controlled by the Strangelove Team",
      "denomUnits": [
        {
          "denom": "transfer/channel-6/ulove"
        },
        {
          "denom": "transfer/channel-6/love",
          "exponent": 6
        }
      ],
      "base": "transfer/channel-6/ulove",
      "display": "transfer/channel-6/love",
      "name": "Love",
      "symbol": "LOVE",
      "penumbraAssetId": {
        "inner": "Pc1lr9eCdoKTkBJCCia9egZdG/qGdMg4WFDhWmXr7Q8="
      }
    },
    "X0Q9Q0l8kegfiXxSU4PULHulV/36XcWyFk8LgrW19gI=": {
      "denomUnits": [
        {
          "denom": "transfer/channel-5/factory/osmo1zlkzu72774ynac53necz46u4ycqtp36wedrar0/willyz"
        },
        {
          "denom": "transfer/channel-5/willyz",
          "exponent": 6
        }
      ],
      "base": "transfer/channel-5/factory/osmo1zlkzu72774ynac53necz46u4ycqtp36wedrar0/willyz",
      "display": "transfer/channel-5/willyz",
      "name": "Willyz",
      "symbol": "WILLYZ",
      "penumbraAssetId": {
        "inner": "X0Q9Q0l8kegfiXxSU4PULHulV/36XcWyFk8LgrW19gI="
      },
      "images": [
        {
          "png": "https://raw.githubusercontent.com/cosmos/chain-registry/master/testnets/osmosistestnet/images/willyz.png",
          "svg": "https://raw.githubusercontent.com/cosmos/chain-registry/master/testnets/osmosistestnet/images/willyz.svg"
        }
      ]
    },
    "eeD8X4rWeMaC3Oqdw8tyU6YBLryAYCBLwEbiIKoo5Qc=": {
      "denomUnits": [
        {
          "denom": "udelegation_penumbravalid173zelmfxtk7r5mhj0k9n96zh9amkr0aucjtsj9j7rdyuj05f4yyqqg5w63"
        },
        {
          "denom": "mdelegation_penumbravalid173zelmfxtk7r5mhj0k9n96zh9amkr0aucjtsj9j7rdyuj05f4yyqqg5w63",
          "exponent": 3
        },
        {
          "denom": "delegation_penumbravalid173zelmfxtk7r5mhj0k9n96zh9amkr0aucjtsj9j7rdyuj05f4yyqqg5w63",
          "exponent": 6
        }
      ],
      "base": "udelegation_penumbravalid173zelmfxtk7r5mhj0k9n96zh9amkr0aucjtsj9j7rdyuj05f4yyqqg5w63",
      "display": "delegation_penumbravalid173zelmfxtk7r5mhj0k9n96zh9amkr0aucjtsj9j7rdyuj05f4yyqqg5w63",
      "symbol": "delUM(Penumbra Labs CI 2)",
      "penumbraAssetId": {
        "inner": "eeD8X4rWeMaC3Oqdw8tyU6YBLryAYCBLwEbiIKoo5Qc="
      },
      "images": [
        {
          "png": "https://raw.githubusercontent.com/prax-wallet/registry/main/images/penumbra-favicon.png"
        }
      ]
    },
    "iU8SGp8cljkRWVH6MJmKG0pH1MEO4LQpSESJKuWsFQY=": {
      "description": "USDLR is a fiat-backed stablecoin issued by Stable. Stable pays DeFi protocols who distribute USDLR.",
      "denomUnits": [
        {
          "denom": "transfer/channel-6/uusdlr"
        },
        {
          "denom": "transfer/channel-6/usdlr",
          "exponent": 6
        }
      ],
      "base": "transfer/channel-6/uusdlr",
      "display": "transfer/channel-6/usdlr",
      "name": "USDLR by Stable",
      "symbol": "USDLR",
      "penumbraAssetId": {
        "inner": "iU8SGp8cljkRWVH6MJmKG0pH1MEO4LQpSESJKuWsFQY="
      },
      "images": [
        {
          "png": "https://raw.githubusercontent.com/cosmos/chain-registry/master/testnets/nobletestnet/images/usdlr.png",
          "svg": "https://raw.githubusercontent.com/cosmos/chain-registry/master/testnets/nobletestnet/images/usdlr.svg"
        }
      ]
    },
    "nDjzm+ldIrNMJha1anGMDVxpA5cLCPnUYQ1clmHF1gw=": {
      "denomUnits": [
        {
          "denom": "pizza"
        }
      ],
      "base": "pizza",
      "display": "pizza",
      "symbol": "PIZZA",
      "penumbraAssetId": {
        "inner": "nDjzm+ldIrNMJha1anGMDVxpA5cLCPnUYQ1clmHF1gw="
      },
      "images": [
        {
          "svg": "https://raw.githubusercontent.com/prax-wallet/registry/main/images/pizza.svg"
        }
      ]
    },
    "nwPDkQq3OvLnBwGTD+nmv1Ifb2GEmFCgNHrU++9BsRE=": {
      "denomUnits": [
        {
          "denom": "gn",
          "exponent": 6
        },
        {
          "denom": "mgn",
          "exponent": 3
        },
        {
          "denom": "ugn"
        }
      ],
      "base": "ugn",
      "display": "gn",
      "symbol": "GN",
      "penumbraAssetId": {
        "inner": "nwPDkQq3OvLnBwGTD+nmv1Ifb2GEmFCgNHrU++9BsRE="
      },
      "images": [
        {
          "svg": "https://raw.githubusercontent.com/prax-wallet/registry/main/images/new-moon-face.svg"
        }
      ]
    },
    "o2gZdbhCH70Ry+7iBhkSeHC/PB1LZhgkn7LHC2kEhQc=": {
      "denomUnits": [
        {
          "denom": "test_btc",
          "exponent": 8
        },
        {
          "denom": "test_sat"
        }
      ],
      "base": "test_sat",
      "display": "test_btc",
      "symbol": "TestBTC",
      "penumbraAssetId": {
        "inner": "o2gZdbhCH70Ry+7iBhkSeHC/PB1LZhgkn7LHC2kEhQc="
      }
    },
    "pmpygqUf4DL+z849rGPpudpdK/+FAv8qQ01U2C73kAw=": {
      "denomUnits": [
        {
          "denom": "test_osmo",
          "exponent": 6
        },
        {
          "denom": "mtest_osmo",
          "exponent": 3
        },
        {
          "denom": "utest_osmo"
        }
      ],
      "base": "utest_osmo",
      "display": "test_osmo",
      "symbol": "TestOSMO",
      "penumbraAssetId": {
        "inner": "pmpygqUf4DL+z849rGPpudpdK/+FAv8qQ01U2C73kAw="
      }
    },
    "reum7wQmk/owgvGMWMZn/6RFPV24zIKq3W6In/WwZgg=": {
      "denomUnits": [
        {
          "denom": "test_usd",
          "exponent": 18
        },
        {
          "denom": "wtest_usd"
        }
      ],
      "base": "wtest_usd",
      "display": "test_usd",
      "symbol": "TestUSD",
      "penumbraAssetId": {
        "inner": "reum7wQmk/owgvGMWMZn/6RFPV24zIKq3W6In/WwZgg="
      },
      "images": [
        {
          "svg": "https://raw.githubusercontent.com/prax-wallet/registry/main/images/test-usd.svg"
        }
      ]
    },
    "s82FyPdtSi8r0syejJHbC6PcjKTQ8a5hCbrnROuBxQ8=": {
      "denomUnits": [
        {
          "denom": "udelegation_penumbravalid1sqwq8p8fqxx4aflthtwmu6kte8je7sh4tj7pyd82qpvdap5ajgrsv0q0ja"
        },
        {
          "denom": "mdelegation_penumbravalid1sqwq8p8fqxx4aflthtwmu6kte8je7sh4tj7pyd82qpvdap5ajgrsv0q0ja",
          "exponent": 3
        },
        {
          "denom": "delegation_penumbravalid1sqwq8p8fqxx4aflthtwmu6kte8je7sh4tj7pyd82qpvdap5ajgrsv0q0ja",
          "exponent": 6
        }
      ],
      "base": "udelegation_penumbravalid1sqwq8p8fqxx4aflthtwmu6kte8je7sh4tj7pyd82qpvdap5ajgrsv0q0ja",
      "display": "delegation_penumbravalid1sqwq8p8fqxx4aflthtwmu6kte8je7sh4tj7pyd82qpvdap5ajgrsv0q0ja",
      "symbol": "delUM(Penumbra Labs CI 1)",
      "penumbraAssetId": {
        "inner": "s82FyPdtSi8r0syejJHbC6PcjKTQ8a5hCbrnROuBxQ8="
      },
      "images": [
        {
          "png": "https://raw.githubusercontent.com/prax-wallet/registry/main/images/penumbra-favicon.png"
        }
      ]
    },
    "ypUT1AOtjfwMOKMATACoD9RSvi8jY/YnYGi46CZ/6Q8=": {
      "denomUnits": [
        {
          "denom": "test_atom",
          "exponent": 6
        },
        {
          "denom": "mtest_atom",
          "exponent": 3
        },
        {
          "denom": "utest_atom"
        }
      ],
      "base": "utest_atom",
      "display": "test_atom",
      "symbol": "TestATOM",
      "penumbraAssetId": {
        "inner": "ypUT1AOtjfwMOKMATACoD9RSvi8jY/YnYGi46CZ/6Q8="
      }
    }
  },
  "stakingAssetId": "KeqcLzNx9qSH5+lcJHBB9KNW+YPrBk5dKzvPMiypahA=",
  "numeraires": [
    "reum7wQmk/owgvGMWMZn/6RFPV24zIKq3W6In/WwZgg=",
    "DOqaAC7a90KP3405fvLRG4rumqMB4tzKa7XsU3CcdxE="
  ]
}